blogger_api_cli/__init__.py
blogger_api_cli/__main__.py
blogger_api_cli/api.py
blogger_api_cli/blogger_test.py
blogger_api_cli/config.py
blogger_api_cli/export_search.py
blogger_api_cli/main.py
blogger_api_cli/permission_test.py
blogger_api_cli/test_config.py
blogger_api_cli/xml_to_json.py
blogger_api_cli-0.2.1.dist-info/licenses/LICENSE
blogger_api_cli-0.2.1.dist-info/METADATA
blogger_api_cli-0.2.1.dist-info/WHEEL
blogger_api_cli-0.2.1.dist-info/entry_points.txt
blogger_api_cli-0.2.1.dist-info/top_level.txt
blogger_api_cli-0.2.1.dist-info/RECORD
