Metadata-Version: 2.4
Name: blogger_api_cli
Version: 0.2.1
Summary: A CLI tool for interacting with the Blogger API
Author-email: Asura Codes <tomaszewski-patryk@o2.pl>
License-Expression: MIT
Project-URL: Homepage, https://github.com/Asura-Codes/spa-on-blogger-api/tree/main/blogger_api_cli
Classifier: Programming Language :: Python :: 3
Classifier: Programming Language :: Python :: 3.7
Classifier: Programming Language :: Python :: 3.8
Classifier: Programming Language :: Python :: 3.9
Classifier: Programming Language :: Python :: 3.10
Classifier: Programming Language :: Python :: 3.11
Classifier: Programming Language :: Python :: 3.12
Classifier: Operating System :: OS Independent
Classifier: Development Status :: 4 - Beta
Classifier: Intended Audience :: Developers
Classifier: Topic :: Internet :: WWW/HTTP
Classifier: Topic :: Software Development :: Libraries :: Python Modules
Requires-Python: >=3.7
License-File: LICENSE
Requires-Dist: requests>=2.25.0
Dynamic: license-file
